pystructurizr/__init__.py
pystructurizr/cli.py
pystructurizr/cli_helper.py
pystructurizr/cli_watcher.py
pystructurizr/cloudstorage.py
pystructurizr/dsl.py
pystructurizr/generator.py
pystructurizr/index.html
pystructurizr-0.1.3.data/data/LICENSE.txt
pystructurizr-0.1.3.dist-info/LICENSE.txt
pystructurizr-0.1.3.dist-info/METADATA
pystructurizr-0.1.3.dist-info/WHEEL
pystructurizr-0.1.3.dist-info/entry_points.txt
pystructurizr-0.1.3.dist-info/top_level.txt
pystructurizr-0.1.3.dist-info/RECORD
