Metadata-Version: 2.1
Name: pystructurizr
Version: 0.1.3
Summary: A Python DSL inspired by Structurizr, intended for generating C4 diagrams
Home-page: https://github.com/nielsvanspauwen/pystructurizr
Author: Niels Vanspauwen
Author-email: niels.vanspauwen@gmail.com
License: MIT
Platform: UNKNOWN
Classifier: Development Status :: 3 - Alpha
Classifier: Intended Audience :: Developers
Classifier: License :: OSI Approved :: MIT License
Classifier: Programming Language :: Python :: 3
Classifier: Programming Language :: Python :: 3.6
Classifier: Programming Language :: Python :: 3.7
Classifier: Programming Language :: Python :: 3.8
License-File: LICENSE.txt
